handycsv/__init__.py
handycsv/column_stats.py
handycsv/csv.py
handycsv/grid_stats.py
handycsv-4.4.0.dist-info/LICENSE
handycsv-4.4.0.dist-info/METADATA
handycsv-4.4.0.dist-info/NOTICE
handycsv-4.4.0.dist-info/WHEEL
handycsv-4.4.0.dist-info/top_level.txt
handycsv-4.4.0.dist-info/RECORD
