Metadata-Version: 2.1
Name: handycsv
Version: 4.4.0
Summary: CSV files as objects
Home-page: http://github.com/nicmcd/handycsv
Author: Nic McDonald
Author-email: nicci02@hotmail.com
License: BSD
License-File: LICENSE
License-File: NOTICE
